torchfetch/__init__.py
torchfetch/cli.py
torchfetch/core/cuda_libraries.py
torchfetch/core/environment.py
torchfetch/core/gpu_info.py
torchfetch/core/system_info.py
torchfetch/core/torch_info.py
torchfetch/display/renderer.py
torchfetch/model/info.py
torchfetch-0.1.1.dist-info/WHEEL
torchfetch-0.1.1.dist-info/entry_points.txt
torchfetch-0.1.1.dist-info/METADATA
torchfetch-0.1.1.dist-info/RECORD
