Metadata-Version: 2.3
Name: torchfetch
Version: 0.1.1
Summary: A Cmdline tools to show PyTorch/CUDA/Nvidia GPU info
Requires-Dist: rich
Requires-Dist: typer
Requires-Python: >=3.9
